nonebot_plugin_arktools/__init__.py
nonebot_plugin_arktools/src/__init__.py
nonebot_plugin_arktools/src/help.py
nonebot_plugin_arktools/src/configs/__init__.py
nonebot_plugin_arktools/src/configs/draw_config.py
nonebot_plugin_arktools/src/configs/ocr_config.py
nonebot_plugin_arktools/src/configs/path_config.py
nonebot_plugin_arktools/src/configs/proxy_config.py
nonebot_plugin_arktools/src/configs/scheduler_config.py
nonebot_plugin_arktools/src/core/__init__.py
nonebot_plugin_arktools/src/core/models_v3.py
nonebot_plugin_arktools/src/core/database/__init__.py
nonebot_plugin_arktools/src/core/database/game_sqlite.py
nonebot_plugin_arktools/src/core/database/plugin_sqlite.py
nonebot_plugin_arktools/src/exceptions/__init__.py
nonebot_plugin_arktools/src/game_draw_card/__init__.py
nonebot_plugin_arktools/src/game_guess_operator/__init__.py
nonebot_plugin_arktools/src/game_guess_operator/data_source.py
nonebot_plugin_arktools/src/misc_monster_siren/__init__.py
nonebot_plugin_arktools/src/misc_monster_siren/data_source.py
nonebot_plugin_arktools/src/misc_operator_birthday/__init__.py
nonebot_plugin_arktools/src/tool_announce_push/__init__.py
nonebot_plugin_arktools/src/tool_announce_push/data_source.py
nonebot_plugin_arktools/src/tool_fetch_maa_copilot/__init__.py
nonebot_plugin_arktools/src/tool_fetch_maa_copilot/data_source.py
nonebot_plugin_arktools/src/tool_open_recruitment/__init__.py
nonebot_plugin_arktools/src/tool_open_recruitment/data_source.py
nonebot_plugin_arktools/src/tool_operator_info/__init__.py
nonebot_plugin_arktools/src/tool_operator_info/data_source.py
nonebot_plugin_arktools/src/tool_sanity_notify/__init__.py
nonebot_plugin_arktools/src/utils/__init__.py
nonebot_plugin_arktools/src/utils/database.py
nonebot_plugin_arktools/src/utils/general.py
nonebot_plugin_arktools/src/utils/image.py
nonebot_plugin_arktools/src/utils/update.py
nonebot_plugin_arktools/test/__init__.py
nonebot_plugin_arktools/test/test_database_utils.py
nonebot_plugin_arktools-1.2.0.dist-info/LICENSE
nonebot_plugin_arktools-1.2.0.dist-info/METADATA
nonebot_plugin_arktools-1.2.0.dist-info/WHEEL
nonebot_plugin_arktools-1.2.0.dist-info/top_level.txt
nonebot_plugin_arktools-1.2.0.dist-info/RECORD
