Metadata-Version: 2.1
Name: nonebot-plugin-arktools
Version: 1.2.0
Summary: 基于 OneBot 适配器的 NoneBot2 明日方舟小工具箱插件
Home-page: https://github.com/NumberSir/nonebot_plugin_arktools
Author: Number_Sir
Author-email: Number_Sir@126.com
Keywords: pip,nonebot2,nonebot,nonebot_plugin
Platform: any
Classifier: Programming Language :: Python :: 3
Classifier: License :: OSI Approved :: MIT License
Classifier: Operating System :: OS Independent
Requires-Python: >=3.8
License-File: LICENSE
Requires-Dist: nonebot-adapter-onebot (>=2.2.0)
Requires-Dist: nonebot2 (>=2.0.0rc2)
Requires-Dist: nonebot-plugin-apscheduler (>=0.2.0)
Requires-Dist: nonebot-plugin-imageutils (>=0.1.14)
Requires-Dist: nonebot-plugin-htmlrender (>=0.2.0.1)
Requires-Dist: httpx (>=0.23.1)
Requires-Dist: aiofiles (>=0.8.0)
Requires-Dist: tortoise-orm (>=0.19.3)
Requires-Dist: lxml (>=4.9.2)
Requires-Dist: feedparser (>=6.0.10)
